<Cookbook><Recipe>Apple Brown Betty<Ingredient>b</Ingredient><Ingredient>r</Ingredient><Ingredient>e</Ingredient><Ingredient>a</Ingredient><Ingredient>d</Ingredient><Ingredient> </Ingredient><Ingredient>c</Ingredient><Ingredient>r</Ingredient><Ingredient>u</Ingredient><Ingredient>m</Ingredient><Ingredient>b</Ingredient><Ingredient>s</Ingredient></Recipe><Recipe>Apricots, candied<Ingredient>w</Ingredient><Ingredient>a</Ingredient><Ingredient>t</Ingredient><Ingredient>e</Ingredient><Ingredient>r</Ingredient></Recipe><Recipe>Bread, pumpkin<Ingredient>f</Ingredient><Ingredient>l</Ingredient><Ingredient>o</Ingredient><Ingredient>u</Ingredient><Ingredient>r</Ingredient></Recipe><Recipe>Bread, sourdough starter<Ingredient>f</Ingredient><Ingredient>l</Ingredient><Ingredient>o</Ingredient><Ingredient>u</Ingredient><Ingredient>r</Ingredient></Recipe><Recipe>Cake, chocolate w/cream cheese icing<Ingredient>f</Ingredient><Ingredient>l</Ingredient><Ingredient>o</Ingredient><Ingredient>u</Ingredient><Ingredient>r</Ingredient></Recipe><Recipe>Cake, chocolate w/vanilla icing<Ingredient>f</Ingredient><Ingredient>l</Ingredient><Ingredient>o</Ingredient><Ingredient>u</Ingredient><Ingredient>r</Ingredient></Recipe><Recipe>Cake, chocolate, pudding<Ingredient>p</Ingredient><Ingredient>u</Ingredient><Ingredient>d</Ingredient><Ingredient>d</Ingredient><Ingredient>i</Ingredient><Ingredient>n</Ingredient><Ingredient>g</Ingredient><Ingredient> </Ingredient><Ingredient>m</Ingredient><Ingredient>i</Ingredient><Ingredient>x</Ingredient></Recipe><Recipe>Cake, chocolate, w/fluffy white icing<Ingredient>f</Ingredient><Ingredient>l</Ingredient><Ingredient>o</Ingredient><Ingredient>u</Ingredient><Ingredient>r</Ingredient></Recipe><Recipe>Cake, marble, w/chocolate icing<Ingredient>f</Ingredient><Ingredient>l</Ingredient><Ingredient>o</Ingredient><Ingredient>u</Ingredient><Ingredient>r</Ingredient></Recipe><Recipe>Cake, white, w/chocolate icing<Ingredient>b</Ingredient><Ingredient>u</Ingredient><Ingredient>t</Ingredient><Ingredient>t</Ingredient><Ingredient>e</Ingredient><Ingredient>r</Ingredient></Recipe><Recipe>Candy, divinity<Ingredient>s</Ingredient><Ingredient>u</Ingredient><Ingredient>g</Ingredient><Ingredient>a</Ingredient><Ingredient>r</Ingredient></Recipe><Recipe>Candy, pralines<Ingredient>p</Ingredient><Ingredient>e</Ingredient><Ingredient>c</Ingredient><Ingredient>a</Ingredient><Ingredient>n</Ingredient><Ingredient>s</Ingredient></Recipe><Recipe>Candy, taffy<Ingredient>s</Ingredient><Ingredient>u</Ingredient><Ingredient>g</Ingredient><Ingredient>a</Ingredient><Ingredient>r</Ingredient></Recipe><Recipe>Cookie, snickerdoodle<Ingredient>b</Ingredient><Ingredient>u</Ingredient><Ingredient>t</Ingredient><Ingredient>t</Ingredient><Ingredient>e</Ingredient><Ingredient>r</Ingredient></Recipe><Recipe>Crisp, apple<Ingredient>a</Ingredient><Ingredient>p</Ingredient><Ingredient>p</Ingredient><Ingredient>l</Ingredient><Ingredient>e</Ingredient></Recipe><Recipe>Crisp, apricot<Ingredient>f</Ingredient><Ingredient>l</Ingredient><Ingredient>o</Ingredient><Ingredient>u</Ingredient><Ingredient>r</Ingredient></Recipe><Recipe>Crisp, peach<Ingredient>f</Ingredient><Ingredient>l</Ingredient><Ingredient>o</Ingredient><Ingredient>u</Ingredient><Ingredient>r</Ingredient></Recipe><Recipe>Dish, crepe, meat filled<Ingredient>e</Ingredient><Ingredient>g</Ingredient><Ingredient>g</Ingredient></Recipe><Recipe>Dish, manicotti w/cheese filling<Ingredient>p</Ingredient><Ingredient>a</Ingredient><Ingredient>s</Ingredient><Ingredient>t</Ingredient><Ingredient>a</Ingredient></Recipe><Recipe>Dish, moussaka, lamb &amp; eggplant<Ingredient>e</Ingredient><Ingredient>g</Ingredient><Ingredient>g</Ingredient><Ingredient>p</Ingredient><Ingredient>l</Ingredient><Ingredient>a</Ingredient><Ingredient>n</Ingredient><Ingredient>t</Ingredient></Recipe><Recipe>Dish, souffle, cheese<Ingredient>w</Ingredient><Ingredient>h</Ingredient><Ingredient>i</Ingredient><Ingredient>t</Ingredient><Ingredient>e</Ingredient><Ingredient> </Ingredient><Ingredient>s</Ingredient><Ingredient>a</Ingredient><Ingredient>u</Ingredient><Ingredient>c</Ingredient><Ingredient>e</Ingredient></Recipe><Recipe>Dish, spaghetti w/meatballs<Ingredient>p</Ingredient><Ingredient>a</Ingredient><Ingredient>s</Ingredient><Ingredient>t</Ingredient><Ingredient>a</Ingredient></Recipe><Recipe>Figs, candied<Ingredient>w</Ingredient><Ingredient>a</Ingredient><Ingredient>t</Ingredient><Ingredient>e</Ingredient><Ingredient>r</Ingredient></Recipe><Recipe>Fudge, peanut butter<Ingredient>s</Ingredient><Ingredient>u</Ingredient><Ingredient>g</Ingredient><Ingredient>a</Ingredient><Ingredient>r</Ingredient></Recipe><Recipe>Fudge, w/marshmallows<Ingredient>s</Ingredient><Ingredient>u</Ingredient><Ingredient>g</Ingredient><Ingredient>a</Ingredient><Ingredient>r</Ingredient></Recipe><Recipe>Fudge, w/nuts brown sugar<Ingredient>s</Ingredient><Ingredient>u</Ingredient><Ingredient>g</Ingredient><Ingredient>a</Ingredient><Ingredient>r</Ingredient></Recipe><Recipe>Gelatin Pops, fzn<Ingredient>g</Ingredient><Ingredient>e</Ingredient><Ingredient>l</Ingredient><Ingredient>a</Ingredient><Ingredient>t</Ingredient><Ingredient>i</Ingredient><Ingredient>n</Ingredient></Recipe><Recipe>Instant Breakfast, prep w/1% milk<Ingredient>d</Ingredient><Ingredient>r</Ingredient><Ingredient>i</Ingredient><Ingredient>n</Ingredient><Ingredient>k</Ingredient><Ingredient> </Ingredient><Ingredient>m</Ingredient><Ingredient>i</Ingredient><Ingredient>x</Ingredient></Recipe><Recipe>Instant Breakfast, prep w/2% milk<Ingredient>d</Ingredient><Ingredient>r</Ingredient><Ingredient>i</Ingredient><Ingredient>n</Ingredient><Ingredient>k</Ingredient><Ingredient> </Ingredient><Ingredient>m</Ingredient><Ingredient>i</Ingredient><Ingredient>x</Ingredient></Recipe><Recipe>Instant Breakfast, prep w/whole milk<Ingredient>d</Ingredient><Ingredient>r</Ingredient><Ingredient>i</Ingredient><Ingredient>n</Ingredient><Ingredient>k</Ingredient><Ingredient> </Ingredient><Ingredient>m</Ingredient><Ingredient>i</Ingredient><Ingredient>x</Ingredient></Recipe><Recipe>Mixed Drink, Bloody Mary<Ingredient>j</Ingredient><Ingredient>u</Ingredient><Ingredient>i</Ingredient><Ingredient>c</Ingredient><Ingredient>e</Ingredient></Recipe><Recipe>Mixed Drink, Gin &amp; Tonic<Ingredient>g</Ingredient><Ingredient>i</Ingredient><Ingredient>n</Ingredient></Recipe><Recipe>Mixed Drink, Manhattan<Ingredient>w</Ingredient><Ingredient>h</Ingredient><Ingredient>i</Ingredient><Ingredient>s</Ingredient><Ingredient>k</Ingredient><Ingredient>e</Ingredient><Ingredient>y</Ingredient></Recipe><Recipe>Mixed Drink, Martini<Ingredient>g</Ingredient><Ingredient>i</Ingredient><Ingredient>n</Ingredient></Recipe><Recipe>Mixed Drink, Tom Collins<Ingredient>j</Ingredient><Ingredient>u</Ingredient><Ingredient>i</Ingredient><Ingredient>c</Ingredient><Ingredient>e</Ingredient></Recipe><Recipe>Pears, candied<Ingredient>p</Ingredient><Ingredient>e</Ingredient><Ingredient>a</Ingredient><Ingredient>r</Ingredient><Ingredient>s</Ingredient></Recipe><Recipe>Pie, butterscotch<Ingredient>p</Ingredient><Ingredient>u</Ingredient><Ingredient>d</Ingredient><Ingredient>d</Ingredient><Ingredient>i</Ingredient><Ingredient>n</Ingredient><Ingredient>g</Ingredient><Ingredient> </Ingredient><Ingredient>m</Ingredient><Ingredient>i</Ingredient><Ingredient>x</Ingredient></Recipe><Recipe>Pie, lemon chiffon<Ingredient>p</Ingredient><Ingredient>i</Ingredient><Ingredient>e</Ingredient><Ingredient> </Ingredient><Ingredient>c</Ingredient><Ingredient>r</Ingredient><Ingredient>u</Ingredient><Ingredient>s</Ingredient><Ingredient>t</Ingredient></Recipe><Recipe>Pie, rhubarb<Ingredient>p</Ingredient><Ingredient>i</Ingredient><Ingredient>e</Ingredient><Ingredient> </Ingredient><Ingredient>c</Ingredient><Ingredient>r</Ingredient><Ingredient>u</Ingredient><Ingredient>s</Ingredient><Ingredient>t</Ingredient></Recipe><Recipe>Pie, strawberry chiffon<Ingredient>s</Ingredient><Ingredient>t</Ingredient><Ingredient>r</Ingredient><Ingredient>a</Ingredient><Ingredient>w</Ingredient><Ingredient>b</Ingredient><Ingredient>e</Ingredient><Ingredient>r</Ingredient><Ingredient>r</Ingredient><Ingredient>i</Ingredient><Ingredient>e</Ingredient><Ingredient>s</Ingredient></Recipe><Recipe>Popover, w/2% milk<Ingredient>f</Ingredient><Ingredient>l</Ingredient><Ingredient>o</Ingredient><Ingredient>u</Ingredient><Ingredient>r</Ingredient></Recipe><Recipe>Popover, w/whole milk<Ingredient>f</Ingredient><Ingredient>l</Ingredient><Ingredient>o</Ingredient><Ingredient>u</Ingredient><Ingredient>r</Ingredient></Recipe><Recipe>Pudding, bread<Ingredient>b</Ingredient><Ingredient>r</Ingredient><Ingredient>e</Ingredient><Ingredient>a</Ingredient><Ingredient>d</Ingredient></Recipe><Recipe>Salad, gelatin, fruity<Ingredient>s</Ingredient><Ingredient>o</Ingredient><Ingredient>d</Ingredient><Ingredient>a</Ingredient></Recipe><Recipe>Salad, waldorf<Ingredient>m</Ingredient><Ingredient>a</Ingredient><Ingredient>y</Ingredient><Ingredient>o</Ingredient><Ingredient>n</Ingredient><Ingredient>n</Ingredient><Ingredient>a</Ingredient><Ingredient>i</Ingredient><Ingredient>s</Ingredient><Ingredient>e</Ingredient></Recipe><Recipe>Sandwich, avocado &amp; cheese, on white<Ingredient>s</Ingredient><Ingredient>p</Ingredient><Ingredient>r</Ingredient><Ingredient>o</Ingredient><Ingredient>u</Ingredient><Ingredient>t</Ingredient><Ingredient>s</Ingredient></Recipe><Recipe>Sandwich, avocado &amp; cheese, part wheat<Ingredient>s</Ingredient><Ingredient>p</Ingredient><Ingredient>r</Ingredient><Ingredient>o</Ingredient><Ingredient>u</Ingredient><Ingredient>t</Ingredient><Ingredient>s</Ingredient></Recipe><Recipe>Sandwich, avocado &amp; cheese, whole wheat<Ingredient>s</Ingredient><Ingredient>p</Ingredient><Ingredient>r</Ingredient><Ingredient>o</Ingredient><Ingredient>u</Ingredient><Ingredient>t</Ingredient><Ingredient>s</Ingredient></Recipe><Recipe>Sandwich, beef, patty melt, on rye<Ingredient>b</Ingredient><Ingredient>e</Ingredient><Ingredient>e</Ingredient><Ingredient>f</Ingredient><Ingredient> </Ingredient><Ingredient>p</Ingredient><Ingredient>a</Ingredient><Ingredient>t</Ingredient><Ingredient>t</Ingredient><Ingredient>y</Ingredient></Recipe><Recipe>Sandwich, BLT, on part whole wheat<Ingredient>b</Ingredient><Ingredient>a</Ingredient><Ingredient>c</Ingredient><Ingredient>o</Ingredient><Ingredient>n</Ingredient></Recipe><Recipe>Sandwich, BLT, on white<Ingredient>b</Ingredient><Ingredient>a</Ingredient><Ingredient>c</Ingredient><Ingredient>o</Ingredient><Ingredient>n</Ingredient></Recipe><Recipe>Sandwich, BLT, on whole wheat<Ingredient>b</Ingredient><Ingredient>a</Ingredient><Ingredient>c</Ingredient><Ingredient>o</Ingredient><Ingredient>n</Ingredient></Recipe><Recipe>Sandwich, chicken salad, on part wheat<Ingredient>l</Ingredient><Ingredient>u</Ingredient><Ingredient>n</Ingredient><Ingredient>c</Ingredient><Ingredient>h</Ingredient><Ingredient>m</Ingredient><Ingredient>e</Ingredient><Ingredient>a</Ingredient><Ingredient>t</Ingredient><Ingredient> </Ingredient><Ingredient>s</Ingredient><Ingredient>p</Ingredient><Ingredient>r</Ingredient><Ingredient>e</Ingredient><Ingredient>a</Ingredient><Ingredient>d</Ingredient></Recipe><Recipe>Sandwich, chicken salad, on white<Ingredient>l</Ingredient><Ingredient>u</Ingredient><Ingredient>n</Ingredient><Ingredient>c</Ingredient><Ingredient>h</Ingredient><Ingredient>m</Ingredient><Ingredient>e</Ingredient><Ingredient>a</Ingredient><Ingredient>t</Ingredient><Ingredient> </Ingredient><Ingredient>s</Ingredient><Ingredient>p</Ingredient><Ingredient>r</Ingredient><Ingredient>e</Ingredient><Ingredient>a</Ingredient><Ingredient>d</Ingredient></Recipe><Recipe>Sandwich, chicken salad, on whole wheat<Ingredient>l</Ingredient><Ingredient>u</Ingredient><Ingredient>n</Ingredient><Ingredient>c</Ingredient><Ingredient>h</Ingredient><Ingredient>m</Ingredient><Ingredient>e</Ingredient><Ingredient>a</Ingredient><Ingredient>t</Ingredient><Ingredient> </Ingredient><Ingredient>s</Ingredient><Ingredient>p</Ingredient><Ingredient>r</Ingredient><Ingredient>e</Ingredient><Ingredient>a</Ingredient><Ingredient>d</Ingredient></Recipe><Recipe>Sandwich, corned beef &amp; swiss, on rye<Ingredient>m</Ingredient><Ingredient>a</Ingredient><Ingredient>y</Ingredient><Ingredient>o</Ingredient><Ingredient>n</Ingredient><Ingredient>n</Ingredient><Ingredient>a</Ingredient><Ingredient>i</Ingredient><Ingredient>s</Ingredient><Ingredient>e</Ingredient></Recipe><Recipe>Sandwich, egg salad, on part wheat<Ingredient>e</Ingredient><Ingredient>g</Ingredient><Ingredient>g</Ingredient><Ingredient> </Ingredient><Ingredient>s</Ingredient><Ingredient>a</Ingredient><Ingredient>l</Ingredient><Ingredient>a</Ingredient><Ingredient>d</Ingredient></Recipe><Recipe>Sandwich, egg salad, on white<Ingredient>e</Ingredient><Ingredient>g</Ingredient><Ingredient>g</Ingredient><Ingredient> </Ingredient><Ingredient>s</Ingredient><Ingredient>a</Ingredient><Ingredient>l</Ingredient><Ingredient>a</Ingredient><Ingredient>d</Ingredient></Recipe><Recipe>Sandwich, egg salad, on whole wheat<Ingredient>e</Ingredient><Ingredient>g</Ingredient><Ingredient>g</Ingredient><Ingredient> </Ingredient><Ingredient>s</Ingredient><Ingredient>a</Ingredient><Ingredient>l</Ingredient><Ingredient>a</Ingredient><Ingredient>d</Ingredient></Recipe><Recipe>Sandwich, grilled cheese, part wheat<Ingredient>c</Ingredient><Ingredient>h</Ingredient><Ingredient>e</Ingredient><Ingredient>e</Ingredient><Ingredient>s</Ingredient><Ingredient>e</Ingredient></Recipe><Recipe>Sandwich, grilled cheese, white<Ingredient>c</Ingredient><Ingredient>h</Ingredient><Ingredient>e</Ingredient><Ingredient>e</Ingredient><Ingredient>s</Ingredient><Ingredient>e</Ingredient></Recipe><Recipe>Sandwich, grilled cheese, whole wheat<Ingredient>c</Ingredient><Ingredient>h</Ingredient><Ingredient>e</Ingredient><Ingredient>e</Ingredient><Ingredient>s</Ingredient><Ingredient>e</Ingredient></Recipe><Recipe>Sandwich, ham &amp; cheese, on part wheat<Ingredient>l</Ingredient><Ingredient>u</Ingredient><Ingredient>n</Ingredient><Ingredient>c</Ingredient><Ingredient>h</Ingredient><Ingredient>m</Ingredient><Ingredient>e</Ingredient><Ingredient>a</Ingredient><Ingredient>t</Ingredient></Recipe><Recipe>Sandwich, ham &amp; cheese, on wheat<Ingredient>l</Ingredient><Ingredient>u</Ingredient><Ingredient>n</Ingredient><Ingredient>c</Ingredient><Ingredient>h</Ingredient><Ingredient>m</Ingredient><Ingredient>e</Ingredient><Ingredient>a</Ingredient><Ingredient>t</Ingredient></Recipe><Recipe>Sandwich, ham &amp; cheese, on white<Ingredient>l</Ingredient><Ingredient>u</Ingredient><Ingredient>n</Ingredient><Ingredient>c</Ingredient><Ingredient>h</Ingredient><Ingredient>m</Ingredient><Ingredient>e</Ingredient><Ingredient>a</Ingredient><Ingredient>t</Ingredient></Recipe><Recipe>Sandwich, ham &amp; swiss, on rye<Ingredient>l</Ingredient><Ingredient>u</Ingredient><Ingredient>n</Ingredient><Ingredient>c</Ingredient><Ingredient>h</Ingredient><Ingredient>m</Ingredient><Ingredient>e</Ingredient><Ingredient>a</Ingredient><Ingredient>t</Ingredient></Recipe><Recipe>Sandwich, ham salad, on part wheat<Ingredient>l</Ingredient><Ingredient>u</Ingredient><Ingredient>n</Ingredient><Ingredient>c</Ingredient><Ingredient>h</Ingredient><Ingredient>m</Ingredient><Ingredient>e</Ingredient><Ingredient>a</Ingredient><Ingredient>t</Ingredient><Ingredient> </Ingredient><Ingredient>s</Ingredient><Ingredient>p</Ingredient><Ingredient>r</Ingredient><Ingredient>e</Ingredient><Ingredient>a</Ingredient><Ingredient>d</Ingredient></Recipe><Recipe>Sandwich, ham salad, on white<Ingredient>l</Ingredient><Ingredient>u</Ingredient><Ingredient>n</Ingredient><Ingredient>c</Ingredient><Ingredient>h</Ingredient><Ingredient>m</Ingredient><Ingredient>e</Ingredient><Ingredient>a</Ingredient><Ingredient>t</Ingredient><Ingredient> </Ingredient><Ingredient>s</Ingredient><Ingredient>p</Ingredient><Ingredient>r</Ingredient><Ingredient>e</Ingredient><Ingredient>a</Ingredient><Ingredient>d</Ingredient></Recipe><Recipe>Sandwich, ham salad, on whole wheat<Ingredient>l</Ingredient><Ingredient>u</Ingredient><Ingredient>n</Ingredient><Ingredient>c</Ingredient><Ingredient>h</Ingredient><Ingredient>m</Ingredient><Ingredient>e</Ingredient><Ingredient>a</Ingredient><Ingredient>t</Ingredient><Ingredient> </Ingredient><Ingredient>s</Ingredient><Ingredient>p</Ingredient><Ingredient>r</Ingredient><Ingredient>e</Ingredient><Ingredient>a</Ingredient><Ingredient>d</Ingredient></Recipe><Recipe>Sandwich, ham, on part wheat<Ingredient>l</Ingredient><Ingredient>u</Ingredient><Ingredient>n</Ingredient><Ingredient>c</Ingredient><Ingredient>h</Ingredient><Ingredient>m</Ingredient><Ingredient>e</Ingredient><Ingredient>a</Ingredient><Ingredient>t</Ingredient></Recipe><Recipe>Sandwich, ham, on rye<Ingredient>l</Ingredient><Ingredient>u</Ingredient><Ingredient>n</Ingredient><Ingredient>c</Ingredient><Ingredient>h</Ingredient><Ingredient>m</Ingredient><Ingredient>e</Ingredient><Ingredient>a</Ingredient><Ingredient>t</Ingredient></Recipe><Recipe>Sandwich, ham, on white<Ingredient>l</Ingredient><Ingredient>u</Ingredient><Ingredient>n</Ingredient><Ingredient>c</Ingredient><Ingredient>h</Ingredient><Ingredient>m</Ingredient><Ingredient>e</Ingredient><Ingredient>a</Ingredient><Ingredient>t</Ingredient></Recipe><Recipe>Sandwich, ham, on whole wheat<Ingredient>l</Ingredient><Ingredient>u</Ingredient><Ingredient>n</Ingredient><Ingredient>c</Ingredient><Ingredient>h</Ingredient><Ingredient>m</Ingredient><Ingredient>e</Ingredient><Ingredient>a</Ingredient><Ingredient>t</Ingredient></Recipe><Recipe>Sandwich, peanut butter/jam, on white<Ingredient>b</Ingredient><Ingredient>r</Ingredient><Ingredient>e</Ingredient><Ingredient>a</Ingredient><Ingredient>d</Ingredient></Recipe><Recipe>Sandwich, peanut butter/jam, part wheat<Ingredient>b</Ingredient><Ingredient>r</Ingredient><Ingredient>e</Ingredient><Ingredient>a</Ingredient><Ingredient>d</Ingredient></Recipe><Recipe>Sandwich, peanut butter/jam, whole wheat<Ingredient>b</Ingredient><Ingredient>r</Ingredient><Ingredient>e</Ingredient><Ingredient>a</Ingredient><Ingredient>d</Ingredient></Recipe><Recipe>Sandwich, roast beef, on part wheat<Ingredient>l</Ingredient><Ingredient>u</Ingredient><Ingredient>n</Ingredient><Ingredient>c</Ingredient><Ingredient>h</Ingredient><Ingredient>m</Ingredient><Ingredient>e</Ingredient><Ingredient>a</Ingredient><Ingredient>t</Ingredient></Recipe><Recipe>Sandwich, roast beef, on white<Ingredient>l</Ingredient><Ingredient>u</Ingredient><Ingredient>n</Ingredient><Ingredient>c</Ingredient><Ingredient>h</Ingredient><Ingredient>m</Ingredient><Ingredient>e</Ingredient><Ingredient>a</Ingredient><Ingredient>t</Ingredient></Recipe><Recipe>Sandwich, roast beef, on whole wheat<Ingredient>l</Ingredient><Ingredient>u</Ingredient><Ingredient>n</Ingredient><Ingredient>c</Ingredient><Ingredient>h</Ingredient><Ingredient>m</Ingredient><Ingredient>e</Ingredient><Ingredient>a</Ingredient><Ingredient>t</Ingredient></Recipe><Recipe>Sandwich, tuna salad, on part wheat<Ingredient>s</Ingredient><Ingredient>p</Ingredient><Ingredient>r</Ingredient><Ingredient>e</Ingredient><Ingredient>a</Ingredient><Ingredient>d</Ingredient></Recipe><Recipe>Sandwich, tuna salad, on white<Ingredient>s</Ingredient><Ingredient>p</Ingredient><Ingredient>r</Ingredient><Ingredient>e</Ingredient><Ingredient>a</Ingredient><Ingredient>d</Ingredient></Recipe><Recipe>Sandwich, tuna salad, on whole wheat<Ingredient>s</Ingredient><Ingredient>p</Ingredient><Ingredient>r</Ingredient><Ingredient>e</Ingredient><Ingredient>a</Ingredient><Ingredient>d</Ingredient></Recipe><Recipe>Sandwich, turkey ham, on part wheat<Ingredient>b</Ingredient><Ingredient>r</Ingredient><Ingredient>e</Ingredient><Ingredient>a</Ingredient><Ingredient>d</Ingredient></Recipe><Recipe>Sandwich, turkey ham, on rye<Ingredient>t</Ingredient><Ingredient>u</Ingredient><Ingredient>r</Ingredient><Ingredient>k</Ingredient><Ingredient>e</Ingredient><Ingredient>y</Ingredient><Ingredient> </Ingredient><Ingredient>h</Ingredient><Ingredient>a</Ingredient><Ingredient>m</Ingredient></Recipe><Recipe>Sandwich, turkey ham, on white<Ingredient>t</Ingredient><Ingredient>u</Ingredient><Ingredient>r</Ingredient><Ingredient>k</Ingredient><Ingredient>e</Ingredient><Ingredient>y</Ingredient><Ingredient> </Ingredient><Ingredient>h</Ingredient><Ingredient>a</Ingredient><Ingredient>m</Ingredient></Recipe><Recipe>Sandwich, turkey ham, on whole wheat<Ingredient>t</Ingredient><Ingredient>u</Ingredient><Ingredient>r</Ingredient><Ingredient>k</Ingredient><Ingredient>e</Ingredient><Ingredient>y</Ingredient><Ingredient> </Ingredient><Ingredient>h</Ingredient><Ingredient>a</Ingredient><Ingredient>m</Ingredient></Recipe><Recipe>Sandwich, turkey ham/cheese, on rye<Ingredient>t</Ingredient><Ingredient>u</Ingredient><Ingredient>r</Ingredient><Ingredient>k</Ingredient><Ingredient>e</Ingredient><Ingredient>y</Ingredient><Ingredient> </Ingredient><Ingredient>h</Ingredient><Ingredient>a</Ingredient><Ingredient>m</Ingredient></Recipe><Recipe>Sandwich, turkey ham/cheese, on white<Ingredient>t</Ingredient><Ingredient>u</Ingredient><Ingredient>r</Ingredient><Ingredient>k</Ingredient><Ingredient>e</Ingredient><Ingredient>y</Ingredient><Ingredient> </Ingredient><Ingredient>h</Ingredient><Ingredient>a</Ingredient><Ingredient>m</Ingredient></Recipe><Recipe>Sandwich, turkey ham/cheese, whole wheat<Ingredient>t</Ingredient><Ingredient>u</Ingredient><Ingredient>r</Ingredient><Ingredient>k</Ingredient><Ingredient>e</Ingredient><Ingredient>y</Ingredient><Ingredient> </Ingredient><Ingredient>h</Ingredient><Ingredient>a</Ingredient><Ingredient>m</Ingredient></Recipe><Recipe>Sandwich, turkey, on part wheat<Ingredient>l</Ingredient><Ingredient>u</Ingredient><Ingredient>n</Ingredient><Ingredient>c</Ingredient><Ingredient>h</Ingredient><Ingredient>m</Ingredient><Ingredient>e</Ingredient><Ingredient>a</Ingredient><Ingredient>t</Ingredient></Recipe><Recipe>Sandwich, turkey, on white<Ingredient>l</Ingredient><Ingredient>u</Ingredient><Ingredient>n</Ingredient><Ingredient>c</Ingredient><Ingredient>h</Ingredient><Ingredient>m</Ingredient><Ingredient>e</Ingredient><Ingredient>a</Ingredient><Ingredient>t</Ingredient></Recipe><Recipe>Sandwich, turkey, on whole wheat<Ingredient>l</Ingredient><Ingredient>u</Ingredient><Ingredient>n</Ingredient><Ingredient>c</Ingredient><Ingredient>h</Ingredient><Ingredient>m</Ingredient><Ingredient>e</Ingredient><Ingredient>a</Ingredient><Ingredient>t</Ingredient></Recipe><Recipe>Sauce, bearnaise<Ingredient>w</Ingredient><Ingredient>i</Ingredient><Ingredient>n</Ingredient><Ingredient>e</Ingredient></Recipe><Recipe>Sauce, bechamel<Ingredient>b</Ingredient><Ingredient>u</Ingredient><Ingredient>t</Ingredient><Ingredient>t</Ingredient><Ingredient>e</Ingredient><Ingredient>r</Ingredient></Recipe><Recipe>Sauce, bordelaise<Ingredient>o</Ingredient><Ingredient>n</Ingredient><Ingredient>i</Ingredient><Ingredient>o</Ingredient><Ingredient>n</Ingredient></Recipe><Recipe>Sauce, curry<Ingredient>f</Ingredient><Ingredient>l</Ingredient><Ingredient>o</Ingredient><Ingredient>u</Ingredient><Ingredient>r</Ingredient></Recipe><Recipe>Sauce, mornay<Ingredient>w</Ingredient><Ingredient>h</Ingredient><Ingredient>i</Ingredient><Ingredient>t</Ingredient><Ingredient>e</Ingredient><Ingredient> </Ingredient><Ingredient>s</Ingredient><Ingredient>a</Ingredient><Ingredient>u</Ingredient><Ingredient>c</Ingredient><Ingredient>e</Ingredient></Recipe><Recipe>Soup, beef stock<Ingredient>b</Ingredient><Ingredient>r</Ingredient><Ingredient>o</Ingredient><Ingredient>t</Ingredient><Ingredient>h</Ingredient></Recipe><Recipe>Soup, menudo, Mexican beef soup<Ingredient>b</Ingredient><Ingredient>e</Ingredient><Ingredient>e</Ingredient><Ingredient>f</Ingredient><Ingredient> </Ingredient><Ingredient>t</Ingredient><Ingredient>r</Ingredient><Ingredient>i</Ingredient><Ingredient>p</Ingredient><Ingredient>e</Ingredient></Recipe><Recipe>Stew, Brunswick<Ingredient>f</Ingredient><Ingredient>a</Ingredient><Ingredient>t</Ingredient></Recipe><Recipe>Sweet Roll, cinnamon, w/raisins walnuts<Ingredient>m</Ingredient><Ingredient>i</Ingredient><Ingredient>l</Ingredient><Ingredient>k</Ingredient></Recipe><Recipe>Taco, chicken<Ingredient>o</Ingredient><Ingredient>n</Ingredient><Ingredient>i</Ingredient><Ingredient>o</Ingredient><Ingredient>n</Ingredient></Recipe><Recipe>Torte, cherry &amp; cream cheese<Ingredient>c</Ingredient><Ingredient>r</Ingredient><Ingredient>e</Ingredient><Ingredient>a</Ingredient><Ingredient>m</Ingredient><Ingredient> </Ingredient><Ingredient>c</Ingredient><Ingredient>h</Ingredient><Ingredient>e</Ingredient><Ingredient>e</Ingredient><Ingredient>s</Ingredient><Ingredient>e</Ingredient></Recipe><Recipe>Tostada, bean &amp; chicken<Ingredient>t</Ingredient><Ingredient>o</Ingredient><Ingredient>s</Ingredient><Ingredient>t</Ingredient><Ingredient>a</Ingredient><Ingredient>d</Ingredient><Ingredient>a</Ingredient><Ingredient> </Ingredient><Ingredient>s</Ingredient><Ingredient>h</Ingredient><Ingredient>e</Ingredient><Ingredient>l</Ingredient><Ingredient>l</Ingredient></Recipe></Cookbook>